alerta_elastalert.py
alerta_elastalert-0.0.18.dist-info/METADATA
alerta_elastalert-0.0.18.dist-info/WHEEL
alerta_elastalert-0.0.18.dist-info/entry_points.txt
alerta_elastalert-0.0.18.dist-info/top_level.txt
alerta_elastalert-0.0.18.dist-info/zip-safe
alerta_elastalert-0.0.18.dist-info/RECORD
