Metadata-Version: 2.1
Name: alerta-elastalert
Version: 0.0.18
Summary: Alerta webhook for elastalert
Home-page: https://github.com/alerta/alerta-contrib
Author: Shakti Rao
Author-email: shakti_rao@affirmednetworks.com
License: Apache License 2.0
Platform: UNKNOWN
